winiel_rfid_sensor/__init__.py
winiel_rfid_sensor/rfid_sensor.py
winiel_rfid_sensor-0.0.7.dist-info/METADATA
winiel_rfid_sensor-0.0.7.dist-info/WHEEL
winiel_rfid_sensor-0.0.7.dist-info/top_level.txt
winiel_rfid_sensor-0.0.7.dist-info/RECORD
