Metadata-Version: 2.1
Name: winiel-rfid-sensor
Version: 0.0.7
Summary: PYPI tutorial package creation written by winiel
Home-page: https://github.com/winiel
Author: winiel
Author-email: winiel@naver.com 
Keywords: winiel,rfid,sensor
Classifier: Programming Language :: Python :: 3.6
Classifier: Programming Language :: Python :: 3.7
Classifier: Programming Language :: Python :: 3.8
Classifier: Programming Language :: Python :: 3.9
Requires-Python: >=3.9
Requires-Dist: pyserial
Requires-Dist: pyusb
